TraktorBuddy/Collection.py
TraktorBuddy/Color.py
TraktorBuddy/FakeTrack.py
TraktorBuddy/Folder.py
TraktorBuddy/Key.py
TraktorBuddy/Listener.py
TraktorBuddy/NmlFile.py
TraktorBuddy/Playlist.py
TraktorBuddy/Rating.py
TraktorBuddy/Track.py
TraktorBuddy/TraktorHash.py
TraktorBuddy/__about__.py
TraktorBuddy/__init__.py
TraktorBuddy/__main__.py
TraktorBuddy/py.typed
traktorbuddy-2.0.0.dist-info/METADATA
traktorbuddy-2.0.0.dist-info/WHEEL
traktorbuddy-2.0.0.dist-info/entry_points.txt
traktorbuddy-2.0.0.dist-info/licenses/LICENSE
traktorbuddy-2.0.0.dist-info/RECORD
