Metadata-Version: 2.4
Name: TraktorBuddy
Version: 2.0.0
Summary: A helping hand for managing Traktor collections.
Project-URL: Source Code, https://code.malenfant.net/didier/TraktorBuddy
Project-URL: Bug Tracker, https://code.malenfant.net/didier/TraktorBuddy/issues
Author-email: Didier Malenfant <didier@malenfant.net>
License-Expression: GPL-3.0-or-later
License-File: LICENSE
Keywords: dj,traktor
Classifier: Development Status :: 5 - Production/Stable
Classifier: Programming Language :: Python
Classifier: Programming Language :: Python :: Implementation :: CPython
Classifier: Programming Language :: Python :: Implementation :: PyPy
Requires-Python: >=3.8
Requires-Dist: dm-py-utilities>=2.2.0
Requires-Dist: mutagen
Requires-Dist: pillow
Requires-Dist: pytz
Requires-Dist: semver
Requires-Dist: traktor-nowplaying
